LICENSE
submit_cgap/__init__.py
submit_cgap/base.py
submit_cgap/exceptions.py
submit_cgap/portal_network_access.py
submit_cgap/scripts/__init__.py
submit_cgap/scripts/check_submission.py
submit_cgap/scripts/make_sample_fastq_file.py
submit_cgap/scripts/resume_uploads.py
submit_cgap/scripts/show_upload_info.py
submit_cgap/scripts/submit_genelist.py
submit_cgap/scripts/submit_metadata_bundle.py
submit_cgap/scripts/submit_ontology.py
submit_cgap/scripts/upload_item_data.py
submit_cgap/submission.py
submit_cgap/tests/__init__.py
submit_cgap/tests/data/cgap_submit_simple.xlsx
submit_cgap/tests/data/cgap_submit_simple2.xlsx
submit_cgap/tests/data/cgap_submit_test.xlsx
submit_cgap/tests/data/cgap_submit_test_with_errors.xlsx
submit_cgap/tests/data/f1_R1.fastq.gz
submit_cgap/tests/data/f1_R2.fastq.gz
submit_cgap/tests/data/f2_R1.fastq.gz
submit_cgap/tests/data/f2_R2.fastq.gz
submit_cgap/tests/data/simulated_bundle.json
submit_cgap/tests/data/test1_R1.fastq.gz
submit_cgap/tests/data/test1_R2.fastq.gz
submit_cgap/tests/test_base.py
submit_cgap/tests/test_check_submission.py
submit_cgap/tests/test_exceptions.py
submit_cgap/tests/test_make_sample_fastq_file.py
submit_cgap/tests/test_resume_uploads.py
submit_cgap/tests/test_show_upload_info.py
submit_cgap/tests/test_submission.py
submit_cgap/tests/test_submit_genelist.py
submit_cgap/tests/test_submit_metadata_bundle.py
submit_cgap/tests/test_submit_ontology.py
submit_cgap/tests/test_testing_helpers.py
submit_cgap/tests/test_upload_item_data.py
submit_cgap/tests/test_utils.py
submit_cgap/tests/test_version.py
submit_cgap/tests/testing_helpers.py
submit_cgap/utils.py
submit_cgap-4.2.0.dist-info/LICENSE
submit_cgap-4.2.0.dist-info/METADATA
submit_cgap-4.2.0.dist-info/WHEEL
submit_cgap-4.2.0.dist-info/entry_points.txt
submit_cgap-4.2.0.dist-info/RECORD
