Metadata-Version: 2.1
Name: submit_cgap
Version: 4.2.0
Summary: Support for uploading file submissions to the Clinical Genomics Analysis Platform (CGAP).
Home-page: https://github.com/dbmi-bgm/SubmitCGAP
License: MIT
Keywords: submit cgap,submitcgap
Author: 4DN-DCIC Team
Author-email: support@4dnucleome.org
Requires-Python: >=3.8.1,<3.13
Classifier: Development Status :: 4 - Beta
Classifier: Intended Audience :: Developers
Classifier: Intended Audience :: Science/Research
Classifier: License :: OSI Approved :: MIT License
Classifier: Natural Language :: English
Classifier: Programming Language :: Python :: 3
Classifier: Programming Language :: Python :: 3.9
Classifier: Programming Language :: Python :: 3.10
Classifier: Programming Language :: Python :: 3.11
Classifier: Programming Language :: Python :: 3.12
Classifier: Programming Language :: Python :: 3.7
Classifier: Programming Language :: Python :: 3.8
Classifier: Topic :: Database :: Database Engines/Servers
Requires-Dist: awscli (>=1.27.79,<2.0.0)
Requires-Dist: dcicutils (>=8.13.0,<9.0.0)
Requires-Dist: requests (>=2.28.2,<3.0.0)
Project-URL: Repository, https://github.com/dbmi-bgm/SubmitCGAP.git
